embed_client/__init__.py
embed_client/__main__.py
embed_client/adapter_config_factory.py
embed_client/adapter_transport.py
embed_client/async_client.py
embed_client/async_client_api_mixin.py
embed_client/async_client_factory_mixin.py
embed_client/async_client_introspection_mixin.py
embed_client/async_client_lifecycle_mixin.py
embed_client/async_client_queue_mixin.py
embed_client/async_client_response_mixin.py
embed_client/auth.py
embed_client/auth_examples.py
embed_client/cli.py
embed_client/cli_core.py
embed_client/client_factory.py
embed_client/client_factory_examples.py
embed_client/client_factory_helpers.py
embed_client/config.py
embed_client/config_defaults.py
embed_client/config_examples.py
embed_client/config_generator.py
embed_client/config_generator_cli.py
embed_client/config_presets.py
embed_client/config_validator.py
embed_client/config_validator_cli.py
embed_client/constants.py
embed_client/demo_cli.py
embed_client/demo_security_cli.py
embed_client/example_async_usage.py
embed_client/example_async_usage_demo.py
embed_client/example_async_usage_ru.py
embed_client/example_async_usage_ru_demo.py
embed_client/exceptions.py
embed_client/response_normalizer.py
embed_client/response_parsers.py
embed_client/security_cli.py
embed_client/security_cli_core.py
embed_client/ssl_examples.py
embed_client/ssl_manager.py
embed_client-3.1.7.19.dist-info/licenses/LICENSE
embed_client-3.1.7.19.dist-info/METADATA
embed_client-3.1.7.19.dist-info/WHEEL
embed_client-3.1.7.19.dist-info/entry_points.txt
embed_client-3.1.7.19.dist-info/top_level.txt
embed_client-3.1.7.19.dist-info/RECORD
