Metadata-Version: 2.4
Name: embed-client
Version: 3.1.7.19
Summary: Async client for Embedding Service API with comprehensive authentication, SSL/TLS, and mTLS support.
Author-email: Vasiliy Zdanovskiy <vasilyvz@gmail.com>
License-Expression: MIT
Project-URL: Homepage, https://github.com/vasilyvz/embed-client
Project-URL: Repository, https://github.com/vasilyvz/embed-client
Project-URL: Documentation, https://github.com/vasilyvz/embed-client#readme
Project-URL: Bug Tracker, https://github.com/vasilyvz/embed-client/issues
Project-URL: Configuration Reference, https://github.com/vasilyvz/embed-client/blob/main/CONFIGURATION.md
Keywords: embedding,async,client,api,authentication,ssl,tls,mtls,config,generator,validator,configuration
Classifier: Development Status :: 5 - Production/Stable
Classifier: Intended Audience :: Developers
Classifier: Operating System :: OS Independent
Classifier: Programming Language :: Python :: 3
Classifier: Programming Language :: Python :: 3.8
Classifier: Programming Language :: Python :: 3.9
Classifier: Programming Language :: Python :: 3.10
Classifier: Programming Language :: Python :: 3.11
Classifier: Programming Language :: Python :: 3.12
Classifier: Topic :: Software Development :: Libraries :: Python Modules
Classifier: Topic :: Internet :: WWW/HTTP :: HTTP Servers
Classifier: Topic :: Security
Classifier: Topic :: System :: Networking
Requires-Python: >=3.8
License-File: LICENSE
Requires-Dist: PyJWT>=2.0.0
Requires-Dist: cryptography>=3.0.0
Requires-Dist: pydantic>=2.0.0
Requires-Dist: mcp-proxy-adapter>=6.9.102
Provides-Extra: test
Requires-Dist: pytest; extra == "test"
Requires-Dist: pytest-asyncio; extra == "test"
Provides-Extra: dev
Requires-Dist: pytest; extra == "dev"
Requires-Dist: pytest-asyncio; extra == "dev"
Requires-Dist: black; extra == "dev"
Requires-Dist: flake8; extra == "dev"
Requires-Dist: mypy; extra == "dev"
Dynamic: license-file
